code_preview/__init__.py
code_preview/cli.py
code_preview/diff_renderer.py
code_preview/file_utils.py
code_preview/git_utils.py
code_preview-1.0.0.dist-info/licenses/LICENSE
code_preview-1.0.0.dist-info/METADATA
code_preview-1.0.0.dist-info/WHEEL
code_preview-1.0.0.dist-info/entry_points.txt
code_preview-1.0.0.dist-info/top_level.txt
code_preview-1.0.0.dist-info/RECORD
