Metadata-Version: 2.4
Name: code-preview
Version: 1.0.0
Summary: A universal CLI tool to preview uncommitted code changes with rich syntax highlighting — before you commit them.
Author-email: Aryant Tripathi <aryanttripathi@gmail.com>
License-Expression: Apache-2.0
Project-URL: Homepage, https://github.com/Aryant-Tripathi/code-preview
Project-URL: Repository, https://github.com/Aryant-Tripathi/code-preview
Project-URL: Issues, https://github.com/Aryant-Tripathi/code-preview/issues
Project-URL: Documentation, https://github.com/Aryant-Tripathi/code-preview#readme
Keywords: git,diff,cli,developer-tools,code,preview,terminal
Requires-Python: >=3.8
License-File: LICENSE
Requires-Dist: rich>=13.0.0
Requires-Dist: gitpython>=3.1.30
Dynamic: license-file
